[
    {
        "userId": 1,
        "restauId": "3422189698",
        "commentaire": "De tr\u00e8s bonne gaufre !\r\nUn r\u00e9gal ! Je reviendrai.",
        "note": 5
    },
    {
        "userId": 2,
        "restauId": "9136326362",
        "commentaire": "Restaurant avec une ambiance sympathique. Des plats originaux.",
        "note": 4
    },
    {
        "userId": 2,
        "restauId": "2297514170",
        "commentaire": "Tr\u00e8s bon repas !\r\nLe patron est \u00e9galement sympa, on peut obtenir de bonne r\u00e9duction :)",
        "note": 4
    },
    {
        "userId": 3,
        "restauId": "3422189698",
        "commentaire": "Tr\u00e8s petit endroit cosi pour s'arr\u00eater prendre un gouter.\r\nPrix un peu excessif ...",
        "note": 2
    }
]